koodu/__init__.py
koodu/__main__.py
koodu/exceptions.py
koodu/generator/__init__.py
koodu/generator/enums.py
koodu/generator/file.py
koodu/generator/generator.py
koodu/generator/models.py
koodu/generator/utils.py
koodu/models/blog.json
koodu/models/todo.json
koodu/scripts/__init__.py
koodu/scripts/checks.py
koodu/scripts/generate.py
koodu/scripts/main.py
koodu/scripts/utils.py
koodu/templates/django/apiadmin.jinja
koodu/templates/django/apiapps.jinja
koodu/templates/django/apiinit.jinja
koodu/templates/django/apimigrationsinit.jinja
koodu/templates/django/apimodels.jinja
koodu/templates/django/apiserializers.jinja
koodu/templates/django/apitests.jinja
koodu/templates/django/apiurls.jinja
koodu/templates/django/apiviews.jinja
koodu/templates/django/asgi.jinja
koodu/templates/django/config.yaml
koodu/templates/django/confinit.jinja
koodu/templates/django/confurls.jinja
koodu/templates/django/confviews.jinja
koodu/templates/django/manage.jinja
koodu/templates/django/readme.jinja
koodu/templates/django/requirements.jinja
koodu/templates/django/settings.jinja
koodu/templates/django/wsgi.jinja
koodu/templates/express/config.yaml
koodu/templates/express/readme.jinja
koodu/templates/fastapi/config.yaml
koodu/templates/fastapi/database.jinja
koodu/templates/fastapi/dependencies.jinja
koodu/templates/fastapi/docker.jinja
koodu/templates/fastapi/macros/pytype.jinja
koodu/templates/fastapi/main.jinja
koodu/templates/fastapi/make.jinja
koodu/templates/fastapi/manage.jinja
koodu/templates/fastapi/models.jinja
koodu/templates/fastapi/readme.jinja
koodu/templates/fastapi/requirements.jinja
koodu/templates/fastapi/routers.jinja
koodu/templates/fastapi/schemas.jinja
koodu/templates/flask/config.yaml
koodu/templates/flask/configs.jinja
koodu/templates/flask/controllers.jinja
koodu/templates/flask/docker.jinja
koodu/templates/flask/env.jinja
koodu/templates/flask/fields.jinja
koodu/templates/flask/initapi.jinja
koodu/templates/flask/initapp.jinja
koodu/templates/flask/manage.jinja
koodu-0.0.5.dist-info/LICENSE
koodu-0.0.5.dist-info/METADATA
koodu-0.0.5.dist-info/WHEEL
koodu-0.0.5.dist-info/entry_points.txt
koodu-0.0.5.dist-info/RECORD
