Metadata-Version: 2.1
Name: koodu
Version: 0.0.5
Summary: Simple and lightweight code generator engine written in python
Home-page: https://gmwa.github.io/koodu/
License: Apache 2.0
Author: Alex Mboutchouang
Author-email: mboutchouangalex@gmail.com
Requires-Python: >=3.8,<4.0
Classifier: License :: OSI Approved :: MIT License
Classifier: License :: Other/Proprietary License
Classifier: Operating System :: OS Independent
Classifier: Programming Language :: Python
Classifier: Programming Language :: Python :: 3
Classifier: Programming Language :: Python :: 3.8
Classifier: Programming Language :: Python :: 3.9
Classifier: Programming Language :: Python :: 3.10
Classifier: Programming Language :: Python :: 3.11
Classifier: Topic :: Software Development
Classifier: Topic :: Software Development :: Libraries
Requires-Dist: jinja2 (>=3.1.2,<4.0.0)
Requires-Dist: pydantic (>=2.7.3,<3.0.0)
Requires-Dist: pyyaml (>=6.0.1,<7.0.0)
